setup.py
pyadhore/__init__.py
pyadhore/iadhore.py
pyadhore.egg-info/PKG-INFO
pyadhore.egg-info/SOURCES.txt
pyadhore.egg-info/dependency_links.txt
pyadhore.egg-info/requires.txt
pyadhore.egg-info/top_level.txt