Metadata-Version: 1.1
Name: pyadhore
Version: 0.1.1
Summary: pyADHoRe provides a data structure for import and manipulation of i-ADHoRe output.
Home-page: https://github.com/widdowquinn/pyADHoRe
Author: Leighton Pritchard
Author-email: leighton.pritchard@hutton.ac.uk
License: GPLv3
Download-URL: https://github.com/widdowquinn/pyADHoRe/releases
Keywords: genome ortholog synteny i-ADHoRe
Platform: Posix; MacOS X
Classifier: Development Status :: 5 - Production/Stable
Classifier: Environment :: Console
Classifier: Intended Audience :: Science/Research
Classifier: Operating System :: MacOS :: MacOS X
Classifier: Operating System :: POSIX :: Linux
Classifier: Programming Language :: Python
Classifier: Programming Language :: Python :: 2.6
Classifier: Topic :: Scientific/Engineering :: Bio-Informatics
